setup.py
swarmy/__init__.py
swarmy/asserts.py
swarmy/shell.py
swarmy.egg-info/PKG-INFO
swarmy.egg-info/SOURCES.txt
swarmy.egg-info/dependency_links.txt
swarmy.egg-info/top_level.txt