Metadata-Version: 1.0
Name: swarmy
Version: 0.1
Summary: A collection of utils
Home-page: http://github.com/bsandrow/swarmy
Author: Brandon Sandrowicz
Author-email: brandon@sandrowicz.org
License: UNKNOWN
Platform: UNKNOWN
